TesRSA/Crypt.py
TesRSA/Key.py
TesRSA/__init__.py
TesRSA/setup.py
TesRSA-1.1.dist-info/METADATA
TesRSA-1.1.dist-info/WHEEL
TesRSA-1.1.dist-info/top_level.txt
TesRSA-1.1.dist-info/RECORD
