Metadata-Version: 2.1
Name: TesRSA
Version: 1.1
Author: Tes
Classifier: Programming Language :: Python :: 3
Classifier: License :: OSI Approved :: MIT License
Classifier: Operating System :: OS Independent
Requires-Python: >=3.12
Requires-Dist: cryptography
